bitcoinlib/__init__.py
bitcoinlib/blocks.py
bitcoinlib/db.py
bitcoinlib/db_cache.py
bitcoinlib/encoding.py
bitcoinlib/keys.py
bitcoinlib/main.py
bitcoinlib/mnemonic.py
bitcoinlib/networks.py
bitcoinlib/scripts.py
bitcoinlib/transactions.py
bitcoinlib/values.py
bitcoinlib/wallets.py
bitcoinlib/config/VERSION
bitcoinlib/config/__init__.py
bitcoinlib/config/config.py
bitcoinlib/config/opcodes.py
bitcoinlib/config/secp256k1.py
bitcoinlib/config/__pycache__/__init__.cpython-310.pyc
bitcoinlib/config/__pycache__/__init__.cpython-313.pyc
bitcoinlib/config/__pycache__/__init__.cpython-38.pyc
bitcoinlib/config/__pycache__/config.cpython-310.pyc
bitcoinlib/config/__pycache__/config.cpython-313.pyc
bitcoinlib/config/__pycache__/config.cpython-38.pyc
bitcoinlib/config/__pycache__/opcodes.cpython-310.pyc
bitcoinlib/config/__pycache__/opcodes.cpython-313.pyc
bitcoinlib/config/__pycache__/opcodes.cpython-38.pyc
bitcoinlib/config/__pycache__/secp256k1.cpython-310.pyc
bitcoinlib/config/__pycache__/secp256k1.cpython-313.pyc
bitcoinlib/config/__pycache__/secp256k1.cpython-38.pyc
bitcoinlib/data/config.ini
bitcoinlib/data/networks.json
bitcoinlib/data/providers.examples-nownodes.json
bitcoinlib/data/providers.examples.json
bitcoinlib/data/providers.json
bitcoinlib/services/__init__.py
bitcoinlib/services/authproxy.py
bitcoinlib/services/baseclient.py
bitcoinlib/services/bcoin.py
bitcoinlib/services/bitaps.py
bitcoinlib/services/bitcoind.py
bitcoinlib/services/bitcoinlibtest.py
bitcoinlib/services/bitflyer.py
bitcoinlib/services/bitgo.py
bitcoinlib/services/blockbook.py
bitcoinlib/services/blockbook1.py
bitcoinlib/services/blockchaininfo.py
bitcoinlib/services/blockchair.py
bitcoinlib/services/blockcypher.py
bitcoinlib/services/blocksmurfer.py
bitcoinlib/services/blockstream.py
bitcoinlib/services/chainso.py
bitcoinlib/services/cryptoid.py
bitcoinlib/services/dogecoind.py
bitcoinlib/services/electrumx.py
bitcoinlib/services/litecoinblockexplorer.py
bitcoinlib/services/litecoind.py
bitcoinlib-0.7.6.dist-info/licenses/LICENSE
bitcoinlib-0.7.6.dist-info/METADATA
bitcoinlib-0.7.6.dist-info/WHEEL
bitcoinlib-0.7.6.dist-info/entry_points.txt
bitcoinlib-0.7.6.dist-info/top_level.txt
bitcoinlib-0.7.6.dist-info/zip-safe
bitcoinlib-0.7.6.dist-info/RECORD
